kirei/__init__.py
kirei/_app/__init__.py
kirei/_app/cli.py
kirei/_app/web/__init__.py
kirei/_app/web/_component.py
kirei/types/__init__.py
kirei/types/annotated/__init__.py
kirei/types/annotated/_validator.py
kirei/types/basic_types.py
kirei/types/function/__init__.py
kirei/types/function/_func_parser.py
kirei/types/function/_injector.py
kirei/types/function/_inquirer.py
kirei/types/function/_param_annotation.py
kirei/types/function/_replier.py
kirei-0.0.3.dist-info/METADATA
kirei-0.0.3.dist-info/WHEEL
kirei-0.0.3.dist-info/RECORD
